osbtlib/__init__.py
osbtlib/__main__.py
osbtlib/attacker_op.py
osbtlib/browser.py
osbtlib/cli.py
osbtlib/exceptions.py
osbtlib/id_token.py
osbtlib/osbtlib.py
osbtlib/proxy.py
osbtlib/requestbin.py
tests/__init__.py
tests/__main__.py
tests/test_attacker_op.py
tests/test_browser.py
tests/test_id_token.py
tests/test_proxy.py
osbtlib-0.0.4.dist-info/LICENSE
osbtlib-0.0.4.dist-info/METADATA
osbtlib-0.0.4.dist-info/WHEEL
osbtlib-0.0.4.dist-info/top_level.txt
osbtlib-0.0.4.dist-info/RECORD
