Metadata-Version: 2.1
Name: osbtlib
Version: 0.0.4
Summary: Scenario description library for oidc scenario based tester
Author: oidc-scenario-based-tester
Author-email: junki.yuasa@gmail.com
License: MIT
License-File: LICENSE
Requires-Dist: auto-mix-prep >=0.2.0
Requires-Dist: playwright >=1.35.0
Requires-Dist: Requests >=2.31.0
